mssql_cli-0.18.2.data/scripts/mssql-cli
mssql_cli-0.18.2.data/scripts/mssql-cli.bat
mssqlcli/__init__.py
mssqlcli/completion_refresher.py
mssqlcli/config.py
mssqlcli/decorators.py
mssqlcli/encodingutils.py
mssqlcli/filters.py
mssqlcli/key_bindings.py
mssqlcli/localized_strings.py
mssqlcli/main.py
mssqlcli/mssql_cli.py
mssqlcli/mssqlbuffer.py
mssqlcli/mssqlcliclient.py
mssqlcli/mssqlclioptionsparser.py
mssqlcli/mssqlclirc
mssqlcli/mssqlcompleter.py
mssqlcli/mssqlqueries.py
mssqlcli/mssqlstyle.py
mssqlcli/mssqltoolbar.py
mssqlcli/sqltoolsclient.py
mssqlcli/telemetry.py
mssqlcli/telemetry_upload.py
mssqlcli/util.py
mssqlcli/jsonrpc/__init__.py
mssqlcli/jsonrpc/jsonrpcclient.py
mssqlcli/jsonrpc/contracts/__init__.py
mssqlcli/jsonrpc/contracts/connectionservice.py
mssqlcli/jsonrpc/contracts/queryexecutestringservice.py
mssqlcli/jsonrpc/contracts/request.py
mssqlcli/mssqltoolsservice/__init__.py
mssqlcli/mssqltoolsservice/externals.py
mssqlcli/mssqltoolsservice/bin/API-MS-Win-core-xstate-l2-1-0.dll
mssqlcli/mssqltoolsservice/bin/Microsoft.Azure.Management.ResourceManager.dll
mssqlcli/mssqltoolsservice/bin/Microsoft.Azure.Management.Sql.dll
mssqlcli/mssqltoolsservice/bin/Microsoft.Build.Framework.dll
mssqlcli/mssqltoolsservice/bin/Microsoft.Build.dll
mssqlcli/mssqltoolsservice/bin/Microsoft.CSharp.dll
mssqlcli/mssqltoolsservice/bin/Microsoft.Data.Tools.Schema.Sql.dll
mssqlcli/mssqltoolsservice/bin/Microsoft.Data.Tools.Sql.BatchParser.dll
mssqlcli/mssqltoolsservice/bin/Microsoft.Data.Tools.Utilities.dll
mssqlcli/mssqltoolsservice/bin/Microsoft.DiaSymReader.Native.x86.dll
mssqlcli/mssqltoolsservice/bin/Microsoft.DotNet.PlatformAbstractions.dll
mssqlcli/mssqltoolsservice/bin/Microsoft.Extensions.DependencyModel.dll
mssqlcli/mssqltoolsservice/bin/Microsoft.Rest.ClientRuntime.Azure.dll
mssqlcli/mssqltoolsservice/bin/Microsoft.Rest.ClientRuntime.dll
mssqlcli/mssqltoolsservice/bin/Microsoft.SqlServer.BatchParser.dll
mssql_cli-0.18.2.dist-info/LICENSE.txt
mssql_cli-0.18.2.dist-info/METADATA
mssql_cli-0.18.2.dist-info/WHEEL
mssql_cli-0.18.2.dist-info/top_level.txt
mssql_cli-0.18.2.dist-info/RECORD
