Metadata-Version: 2.1
Name: mssql-cli
Version: 0.18.2
Summary: CLI for SQL Server Database. With auto-completion and syntax highlighting.
Home-page: https://github.com/dbcli/mssql-cli
Author: Microsoft Corporation
Author-email: sqlcli@microsoft.com
License: BSD-3
Platform: UNKNOWN
Classifier: Intended Audience :: Developers
Classifier: License :: OSI Approved :: BSD License
Classifier: Operating System :: Unix
Classifier: Programming Language :: Python
Classifier: Programming Language :: Python :: 2.7
Classifier: Programming Language :: Python :: 3
Classifier: Programming Language :: Python :: 3.4
Classifier: Programming Language :: Python :: 3.5
Classifier: Programming Language :: Python :: 3.6
Classifier: Programming Language :: Python :: 3.7
Classifier: Programming Language :: Python :: 3.8
Classifier: Programming Language :: SQL
Classifier: Topic :: Database
Classifier: Topic :: Database :: Front-Ends
Classifier: Topic :: Software Development
Classifier: Topic :: Software Development :: Libraries :: Python Modules
Requires-Dist: click (<7.1,>=4.1)
Requires-Dist: argparse (>=1.2.1)
Requires-Dist: Pygments (>=2.0)
Requires-Dist: prompt-toolkit (<2.1.0,>=2.0.0)
Requires-Dist: sqlparse (<0.3.0,>=0.2.2)
Requires-Dist: configobj (>=5.0.6)
Requires-Dist: humanize (>=0.5.1)
Requires-Dist: cli-helpers (<1.0.0,>=0.2.3)
Requires-Dist: applicationinsights (>=0.11.1)
Requires-Dist: future (>=0.16.0)
Requires-Dist: wheel (>=0.29.0)
Requires-Dist: enum34 (>=1.1.6)
